bamp/__init__.py
bamp/config/__init__.py
bamp/config/bumpversion.py
bamp/config/ini.py
bamp/engine.py
bamp/exc.py
bamp/helpers/__init__.py
bamp/helpers/callbacks.py
bamp/helpers/docs.py
bamp/helpers/ui.py
bamp/logs.py
bamp/main.py
bamp/persistence.py
bamp/vcs/__init__.py
bamp/vcs/git.py
bamp-1.2.0.dist-info/entry_points.txt
bamp-1.2.0.dist-info/LICENSE
bamp-1.2.0.dist-info/WHEEL
bamp-1.2.0.dist-info/METADATA
bamp-1.2.0.dist-info/RECORD
